MANIFEST.in
setup.py
doc/LICENSE
doc/soscleaner.8.gz
scripts/soscleaner
src/soscleaner.py
src/soscleaner.pyc
src/soscleaner.egg-info/PKG-INFO
src/soscleaner.egg-info/SOURCES.txt
src/soscleaner.egg-info/dependency_links.txt
src/soscleaner.egg-info/top_level.txt