Metadata-Version: 1.0
Name: soscleaner
Version: 0.2.2
Summary: To clean and filter sensitive data from a standard sosreport
Home-page: https://github.com/RedHatGov/SOSCleaner
Author: Jamie Duncan
Author-email: jduncan@redhat.com
License: GPLv2
Platform: UNKNOWN
